{
  "titulo_input": "El libro del ego",
  "autor_input": "Osho",
  "isbn_seed": "",
  "isbn_discovered": "6748983085",
  "apple": {
    "ok": true,
    "source": "apple_books",
    "match_score": 0.828125,
    "match_details": {
      "matched_title": "El muro del yo",
      "matched_author": "Osho Taigu"
    },
    "synopsis": "OSHO TAIGU, UN RECONOCIDO MONJE BUDISTA, NOS COMPARTE LOS CONSEJOS FUNDAMENTALES PARA VIVIR CON SERENIDAD. «Solo me suceden cosas que me hacen sufrir.» «Aún me arrepiento por algo del pasado.» «No sé para qué vivo.» ¿Cómo puedes liberarte de pensamientos angustiantes como estos? Osho Taigu nos explica que todo el sufrimiento que sientes en el corazón nace de las ilusiones creadas por tu mente. Sin embargo, si aprendes a observarla con consciencia y a modificar tus reacciones, lograrás una mente serena y en paz y podrás liberarte de los problemas que te aquejan. Es un camino arduo que requiere de valentía, pero al conseguir sobrepasar los muros de la mente y el ego, vivirás por fin libre de toda aflicción y sufrimiento. ESTE ES EL PROPÓSITO DEL BUDISMO.",
    "synopsis_length": 762,
    "covers": [
      {
        "size": "xxlarge",
        "url": "https://is1-ssl.mzstatic.com/image/thumb/Publication221/v4/ea/ac/f3/eaacf30e-be5c-8267-e1ff-c75f85f03a89/9786073861168.jpg/3000x3000bb.jpg"
      },
      {
        "size": "xlarge",
        "url": "https://is1-ssl.mzstatic.com/image/thumb/Publication221/v4/ea/ac/f3/eaacf30e-be5c-8267-e1ff-c75f85f03a89/9786073861168.jpg/1200x1200bb.jpg"
      },
      {
        "size": "large",
        "url": "https://is1-ssl.mzstatic.com/image/thumb/Publication221/v4/ea/ac/f3/eaacf30e-be5c-8267-e1ff-c75f85f03a89/9786073861168.jpg/600x600bb.jpg"
      },
      {
        "size": "medium",
        "url": "https://is1-ssl.mzstatic.com/image/thumb/Publication221/v4/ea/ac/f3/eaacf30e-be5c-8267-e1ff-c75f85f03a89/9786073861168.jpg/100x100bb.jpg"
      }
    ],
    "verified_identity": {
      "titulo_real": "El muro del yo",
      "autor_completo": "Osho Taigu",
      "año": "2025",
      "editorial": null,
      "isbn": "6748983085",
      "categorias": [
        "Superación personal",
        "Libros",
        "Salud, mente y cuerpo"
      ],
      "track_view_url": "https://books.apple.com/mx/book/el-muro-del-yo/id6748983085?uo=4"
    }
  },
  "google": {
    "ok": true,
    "source": "google_books",
    "match_score": 1,
    "match_details": {
      "matched_title": "El Libro Del Ego",
      "matched_author": "Osho"
    },
    "synopsis": "",
    "synopsis_length": 0,
    "covers": [
      {
        "size": "small",
        "url": "https://books.google.com/books/content?id=zcfMAAAACAAJ&printsec=frontcover&img=1&zoom=1&source=gbs_api"
      }
    ],
    "verified_identity": {
      "titulo_real": "El Libro Del Ego",
      "subtitulo": "",
      "autor_completo": "Osho",
      "año": "2005",
      "editorial": "Grijalbo",
      "paginas": null,
      "isbn": "9780307273659",
      "isbn13": "9780307273659",
      "isbn10": "0307273652",
      "categorias": [
        "Ego (Psychology)"
      ],
      "idioma": "es",
      "preview_link": "http://books.google.com/books?id=zcfMAAAACAAJ&dq=El+libro+del+ego+Osho&hl=&cd=1&source=gbs_api"
    }
  },
  "openlibrary": {
    "ok": true,
    "source": "openlibrary",
    "match_score": 1,
    "match_details": {
      "matched_title": "El libro del ego",
      "matched_author": "Osho Osho"
    },
    "synopsis": "Libro verificado en OpenLibrary. Publicado originalmente en 2020.",
    "synopsis_length": 65,
    "covers": [
      {
        "size": "large",
        "url": "https://covers.openlibrary.org/b/id/12334393-L.jpg"
      },
      {
        "size": "medium",
        "url": "https://covers.openlibrary.org/b/id/12334393-M.jpg"
      },
      {
        "size": "small",
        "url": "https://covers.openlibrary.org/b/id/12334393-S.jpg"
      }
    ],
    "verified_identity": {
      "titulo_real": "El libro del ego",
      "autor_completo": "Osho Osho",
      "año": "2020",
      "editorial": null,
      "isbn": "",
      "categorias": [],
      "idioma": null,
      "paginas": null
    }
  },
  "amazon": {
    "ok": true,
    "source": "amazon",
    "match_score": 0.85,
    "covers": [
      {
        "size": "large",
        "url": "https://images-na.ssl-images-amazon.com/images/P/6748983085.01.LZZZZZZZ.jpg"
      }
    ],
    "synopsis": "",
    "synopsis_length": 0,
    "verified_identity": {
      "isbn": "6748983085",
      "titulo_real": null,
      "autor_completo": null,
      "año": null
    }
  },
  "valid_covers": [
    {
      "source": "apple_books",
      "size": "xxlarge",
      "url": "https://is1-ssl.mzstatic.com/image/thumb/Publication221/v4/ea/ac/f3/eaacf30e-be5c-8267-e1ff-c75f85f03a89/9786073861168.jpg/3000x3000bb.jpg",
      "valid": true
    },
    {
      "source": "apple_books",
      "size": "xlarge",
      "url": "https://is1-ssl.mzstatic.com/image/thumb/Publication221/v4/ea/ac/f3/eaacf30e-be5c-8267-e1ff-c75f85f03a89/9786073861168.jpg/1200x1200bb.jpg",
      "valid": true
    },
    {
      "source": "apple_books",
      "size": "large",
      "url": "https://is1-ssl.mzstatic.com/image/thumb/Publication221/v4/ea/ac/f3/eaacf30e-be5c-8267-e1ff-c75f85f03a89/9786073861168.jpg/600x600bb.jpg",
      "valid": true
    },
    {
      "source": "apple_books",
      "size": "medium",
      "url": "https://is1-ssl.mzstatic.com/image/thumb/Publication221/v4/ea/ac/f3/eaacf30e-be5c-8267-e1ff-c75f85f03a89/9786073861168.jpg/100x100bb.jpg",
      "valid": true
    },
    {
      "source": "google_books",
      "size": "small",
      "url": "https://books.google.com/books/content?id=zcfMAAAACAAJ&printsec=frontcover&img=1&zoom=1&source=gbs_api",
      "valid": true
    },
    {
      "source": "openlibrary",
      "size": "large",
      "url": "https://covers.openlibrary.org/b/id/12334393-L.jpg",
      "valid": true
    },
    {
      "source": "openlibrary",
      "size": "medium",
      "url": "https://covers.openlibrary.org/b/id/12334393-M.jpg",
      "valid": true
    },
    {
      "source": "openlibrary",
      "size": "small",
      "url": "https://covers.openlibrary.org/b/id/12334393-S.jpg",
      "valid": true
    },
    {
      "source": "amazon",
      "size": "large",
      "url": "https://images-na.ssl-images-amazon.com/images/P/6748983085.01.LZZZZZZZ.jpg",
      "valid": true
    }
  ],
  "_sources_succeeded": [
    "apple_books",
    "google_books",
    "openlibrary",
    "amazon"
  ],
  "_sources_failed": [],
  "_timing": {
    "phase1_parallel_ms": 1178,
    "phase2_isbn_chain_ms": 168,
    "cover_validation_ms": 728,
    "total_ms": 2074
  },
  "_cached_at": "2026-04-21T11:52:58.289Z"
}